pydatawork.py
pydatawork-0.17.7.3.dist-info/LICENSE.txt
pydatawork-0.17.7.3.dist-info/METADATA
pydatawork-0.17.7.3.dist-info/WHEEL
pydatawork-0.17.7.3.dist-info/top_level.txt
pydatawork-0.17.7.3.dist-info/RECORD
