Metadata-Version: 2.1
Name: pydatawork
Version: 0.17.7.3
Summary: jk.zhou's datawork
Home-page: https://github.com/jkjoker/datawork
Author: jk.zhou
Author-email: zhouqiling.bjfu@foxmail.com
License: MIT
Keywords: datawork
Classifier: Development Status :: 3 - Alpha
Classifier: License :: OSI Approved :: MIT License
Classifier: Programming Language :: Python :: 3.7
License-File: LICENSE.txt
